stem_mixer/__init__.py
stem_mixer/brid_index.txt
stem_mixer/features.py
stem_mixer/metadata.py
stem_mixer/mix.py
stem_mixer/musdb_index.txt
stem_mixer-0.1.0.dist-info/LICENSE.md
stem_mixer-0.1.0.dist-info/METADATA
stem_mixer-0.1.0.dist-info/WHEEL
stem_mixer-0.1.0.dist-info/top_level.txt
stem_mixer-0.1.0.dist-info/RECORD
