Metadata-Version: 2.1
Name: stem_mixer
Version: 0.1.0
Summary: Data augmentation for source separation models
Author-email: Giovana Morais <giovana.morais@nyu.edu>, Lindsey Pietrewicz <lgp3212@nyu.edu>
License: Copyright (c) 2024, stem_mixer development team
Project-URL: Repository, https://github.com/giovana-morais/stem_mixer
Project-URL: Documentation, https://giovana-morais.github.io/stem_mixer
Classifier: Development Status :: 2 - Pre-Alpha
Classifier: License :: OSI Approved :: ISC License (ISCL)
Classifier: Programming Language :: Python
Classifier: Programming Language :: Python :: 3
Requires-Python: >=3.10
License-File: LICENSE.md
Requires-Dist: librosa>=0.10.0
Requires-Dist: pandas
Requires-Dist: soundfile>=0.12.1
Requires-Dist: tqdm
Provides-Extra: dev
Requires-Dist: pip-tools; extra == "dev"
Requires-Dist: pytest; extra == "dev"
Requires-Dist: ruff; extra == "dev"
Provides-Extra: docs
Requires-Dist: sphinx; extra == "docs"
